LICENSE.rst
MANIFEST.in
README.rst
setup.py
RBAC_service.egg-info/PKG-INFO
RBAC_service.egg-info/SOURCES.txt
RBAC_service.egg-info/dependency_links.txt
RBAC_service.egg-info/requires.txt
RBAC_service.egg-info/top_level.txt
rbac_service/__init__.py
rbac_service/admin.py
rbac_service/apps.py
rbac_service/permission_classes.py
rbac_service/tests.py
rbac_service/views.py
rbac_service/migrations/0001_initial.py
rbac_service/migrations/__init__.py
rbac_service/models/__init__.py
rbac_service/models/permission.py
rbac_service/models/role.py
rbac_service/models/user_roles.py